word_count_lib/__init__.py
word_count_lib/__main__.py
word_count_lib/core.py
wordcountlibrs-0.1.0.dist-info/licenses/LICENSE
wordcountlibrs-0.1.0.dist-info/METADATA
wordcountlibrs-0.1.0.dist-info/WHEEL
wordcountlibrs-0.1.0.dist-info/entry_points.txt
wordcountlibrs-0.1.0.dist-info/top_level.txt
wordcountlibrs-0.1.0.dist-info/RECORD
