Metadata-Version: 2.4
Name: WordCountLibRS
Version: 0.1.0
Summary: Count words in a text
Author: Roiuda Sharaf Abutaleb
Author-email: Roiuda Sharaf Abutaleb <abutaleb09n@gmail.com>
License: MIT License
Requires-Python: >=3.7
License-File: LICENSE
Dynamic: author
Dynamic: license-file
Dynamic: requires-python
